figga/__init__.py
figga-0.3.0.dist-info/LICENSE
figga-0.3.0.dist-info/WHEEL
figga-0.3.0.dist-info/METADATA
figga-0.3.0.dist-info/RECORD
