Metadata-Version: 2.1
Name: figga
Version: 0.3.0
Summary: A simple configuration manager for Python.
Home-page: https://github.com/berislavlopac/figga
License: MIT
Keywords: configuration,config
Author: Berislav Lopac
Author-email: berislav@lopac.net
Requires-Python: >=3.7,<4.0
Classifier: License :: OSI Approved :: MIT License
Classifier: Programming Language :: Python :: 3
Classifier: Programming Language :: Python :: 3.7
Classifier: Programming Language :: Python :: 3.8
Classifier: Programming Language :: Python :: 3.9
Project-URL: Repository, https://github.com/berislavlopac/figga
